guardpy/__init__.py
guardpy-0.0.0.dist-info/LICENSE
guardpy-0.0.0.dist-info/METADATA
guardpy-0.0.0.dist-info/WHEEL
guardpy-0.0.0.dist-info/top_level.txt
guardpy-0.0.0.dist-info/RECORD
